shell_pipe.py
shell_pipe-0.1.1.dist-info/LICENSE
shell_pipe-0.1.1.dist-info/METADATA
shell_pipe-0.1.1.dist-info/WHEEL
shell_pipe-0.1.1.dist-info/top_level.txt
shell_pipe-0.1.1.dist-info/RECORD
