Metadata-Version: 2.1
Name: shell-pipe
Version: 0.1.1
Summary: shell like pipe
Home-page: https://gitee.com/yangguosdxl/py_ppipe.git
Author: kellen
Author-email: 591188898@qq.com
License: MIT
Classifier: License :: OSI Approved :: MIT License
Classifier: Programming Language :: Python
Classifier: Programming Language :: Python :: 3
Classifier: Programming Language :: Python :: 3.6
Classifier: Programming Language :: Python :: Implementation :: CPython
Classifier: Programming Language :: Python :: Implementation :: PyPy
Requires-Python: >=3.6.0
License-File: LICENSE
Requires-Dist: subprocess
